haccrypto/_crypto.cpython-37m-i386-linux-gnu.so
haccrypto/crypto.py
haccrypto/openssl-license.txt
haccrypto/__init__.py
haccrypto-0.1.3.dist-info/LICENSE.md
haccrypto-0.1.3.dist-info/RECORD
haccrypto-0.1.3.dist-info/top_level.txt
haccrypto-0.1.3.dist-info/WHEEL
haccrypto-0.1.3.dist-info/METADATA
