Metadata-Version: 2.1
Name: haccrypto
Version: 0.1.3
Summary: Nintendo Switch XTSN crypto for Python
Home-page: https://github.com/luigoalma/haccrypto
Author: luigoalma
License: MIT
Classifier: Topic :: Utilities
Classifier: License :: OSI Approved :: MIT License
Classifier: Programming Language :: Python :: 3
Classifier: Programming Language :: Python :: 3.6
Classifier: Programming Language :: Python :: 3.7
Classifier: Programming Language :: Python :: 3.8
Classifier: Programming Language :: Python :: 3.9
Classifier: Programming Language :: Python :: 3.10
Classifier: Programming Language :: Python :: 3.11
License-File: LICENSE.md
